{
    "name": "AufWallet polkadot chain list",
    "logoURI": "https://assets.aufwallet.com/logo.png",
    "timestamp": "2023-10-30T06:58:13.018Z",
    "data": [
      {
        "name": "Polkadot",
        "symbol": "DOT",
        "decimals": 10,
        "logoURI": "https://assets.aufwallet.com/chains/polkadot/info/logo.png",
        "chainId": "polkadot",
        "coinType": 354,
        "explorer": "https://explorer.polkascan.io/polkadot",
        "rpcUrls": [
          "https://rpc.polkadot.io"
        ],
        "encoders": [
          "ss58:0"
        ],
        "chainType": 2,
        "priceId": "polkadot",
        "features": [
            "ed25519"
        ]
      },
      {
        "name": "Kusama",
        "symbol": "KSM",
        "decimals": 12,
        "logoURI": "https://assets.aufwallet.com/chains/kusama/info/logo.png",
        "chainId": "kusama",
        "coinType": 434,
        "explorer": "https://explorer.polkascan.io/kusama",
        "rpcUrls": [
          "https://rpc.kusama.io"
        ],
        "encoders": [
          "ss58:2"
        ],
        "chainType": 2,
        "priceId": "kusama",
        "features": [
            "ed25519"
        ]
      }
    ],
    "version": {
      "major": 1,
      "minor": 2,
      "patch": 0
    }
  }